exisone/__init__.py
exisone/client.py
exisone/hardware.py
exisone/models.py
exisone/offline.py
exisone/py.typed
exisone_client-0.7.0.dist-info/licenses/LICENSE
exisone_client-0.7.0.dist-info/METADATA
exisone_client-0.7.0.dist-info/WHEEL
exisone_client-0.7.0.dist-info/top_level.txt
exisone_client-0.7.0.dist-info/RECORD
