Metadata-Version: 2.4
Name: exisone-client
Version: 0.7.0
Summary: Python client SDK for ExisOne Software Activation System
Author-email: "Exis, LLC" <support@exisone.com>
Maintainer-email: "Exis, LLC" <support@exisone.com>
License: MIT
Project-URL: Homepage, https://www.exisone.com
Project-URL: Documentation, https://www.exisone.com/docs-sdk.html
Project-URL: Repository, https://github.com/ExisLLC/SoftwareActivationProject
Project-URL: Issues, https://github.com/ExisLLC/SoftwareActivationProject/issues
Keywords: license,activation,exisone,exis,software licensing,license management,software activation
Classifier: Development Status :: 4 - Beta
Classifier: Intended Audience :: Developers
Classifier: License :: OSI Approved :: MIT License
Classifier: Operating System :: OS Independent
Classifier: Programming Language :: Python :: 3
Classifier: Programming Language :: Python :: 3.8
Classifier: Programming Language :: Python :: 3.9
Classifier: Programming Language :: Python :: 3.10
Classifier: Programming Language :: Python :: 3.11
Classifier: Programming Language :: Python :: 3.12
Classifier: Programming Language :: Python :: 3.13
Classifier: Topic :: Software Development :: Libraries :: Python Modules
Classifier: Topic :: System :: Software Distribution
Classifier: Typing :: Typed
Requires-Python: >=3.8
License-File: LICENSE
Requires-Dist: requests>=2.25.0
Requires-Dist: cryptography>=3.4.0
Provides-Extra: dev
Requires-Dist: pytest>=7.0.0; extra == "dev"
Requires-Dist: pytest-cov>=4.0.0; extra == "dev"
Requires-Dist: mypy>=1.0.0; extra == "dev"
Requires-Dist: ruff>=0.1.0; extra == "dev"
Requires-Dist: types-requests>=2.25.0; extra == "dev"
Dynamic: license-file
